brainmaze/__init__.py
brainmaze-0.0.0a0.dist-info/METADATA
brainmaze-0.0.0a0.dist-info/WHEEL
brainmaze-0.0.0a0.dist-info/top_level.txt
brainmaze-0.0.0a0.dist-info/RECORD
